Metadata-Version: 2.2
Name: dash_perspective_component
Version: 0.0.1a0
Summary: Plotly Dash component based on finos/perspective
Author: Abdul Azeem S <azeem.az.19@gmail.com>
License: MIT
Classifier: Framework :: Dash
License-File: LICENSE
Dynamic: author
Dynamic: classifier
Dynamic: description
Dynamic: description-content-type
Dynamic: license
Dynamic: summary
